myp/__init__.py
myp/__main__.py
myp/const.py
myp/globals.py
myp/basis/__init__.py
myp/basis/commands.py
myp/basis/funcs.py
myp/get/__init__.py
myp/get/commands.py
myp/package/__init__.py
myp/package/reader.py
myp/pip/__init__.py
myp/pip/commands.py
myp/scripts/__init__.py
myp/scripts/commands.py
myp/scripts/funcs.py
myp/templates/__init__.py
myp/templates/blank.py
myp/templates/django.py
myp/templates/flaskmng.py
myp/templates/pypi.py
myp-1.5.8.dist-info/LICENSE.txt
myp-1.5.8.dist-info/METADATA
myp-1.5.8.dist-info/WHEEL
myp-1.5.8.dist-info/entry_points.txt
myp-1.5.8.dist-info/top_level.txt
myp-1.5.8.dist-info/RECORD
