Metadata-Version: 2.1
Name: myp
Version: 1.5.8
Summary: Manage your Python apps easily.
Home-page: https://github.com/yunisdev/myp#readme
Author: yunisdev
Author-email: yunisdev.04@gmail.com
License: UNKNOWN
Platform: UNKNOWN
Classifier: Programming Language :: Python :: 3
Classifier: License :: OSI Approved :: MIT License
Classifier: Operating System :: OS Independent
Classifier: Topic :: Software Development
Classifier: Natural Language :: English
Requires-Python: >=3.6
Requires-Dist: PyInquirer
Requires-Dist: click
Requires-Dist: pipenv
Requires-Dist: pipfile
Requires-Dist: prettytable
Requires-Dist: termcolor2
